rcsb/__init__.py
rcsb/utils/__init__.py
rcsb/utils/chem/CactvsMoleculeFactory.py
rcsb/utils/chem/ChemCompDepictWrapper.py
rcsb/utils/chem/ChemCompIndexProvider.py
rcsb/utils/chem/ChemCompMoleculeProvider.py
rcsb/utils/chem/ChemCompSearchIndexProvider.py
rcsb/utils/chem/ChemCompSearchWrapper.py
rcsb/utils/chem/FailList.py
rcsb/utils/chem/IoUtils.py
rcsb/utils/chem/MolecularFormula.py
rcsb/utils/chem/MoleculeAnnotationsCompare.py
rcsb/utils/chem/ObMoleculeFactory.py
rcsb/utils/chem/OeDepict.py
rcsb/utils/chem/OeDepictAlign.py
rcsb/utils/chem/OeIoUtils.py
rcsb/utils/chem/OeMoleculeFactory.py
rcsb/utils/chem/OeMoleculeProvider.py
rcsb/utils/chem/OeSearchMoleculeProvider.py
rcsb/utils/chem/OeSearchUtils.py
rcsb/utils/chem/PdbxChemComp.py
rcsb/utils/chem/PdbxChemCompConstants.py
rcsb/utils/chem/RdMoleculeFactory.py
rcsb/utils/chem/__init__.py
rcsb/utils/chem/cactvsAnnotateMol.py
rcsb.utils.chem-0.41.dist-info/LICENSE
rcsb.utils.chem-0.41.dist-info/METADATA
rcsb.utils.chem-0.41.dist-info/WHEEL
rcsb.utils.chem-0.41.dist-info/dependency_links.txt
rcsb.utils.chem-0.41.dist-info/entry_points.txt
rcsb.utils.chem-0.41.dist-info/top_level.txt
rcsb.utils.chem-0.41.dist-info/RECORD
